guisurfer/agent/base.py
guisurfer/agent/env.py
guisurfer/agent/llm.py
guisurfer/agent/models.py
guisurfer/agent/runtime.py
guisurfer/agent/task.py
guisurfer/agent/types.py
guisurfer/auth/default.py
guisurfer/auth/key.py
guisurfer/auth/provider.py
guisurfer/auth/transport.py
guisurfer/auth/user.py
guisurfer/db/conn.py
guisurfer/db/models.py
guisurfer/job/agent/base.py
guisurfer/job/agent/job.py
guisurfer/job/agent/k8s.py
guisurfer/job/agent/main.py
guisurfer/job/agent/restart.py
guisurfer/job/base.py
guisurfer/job/env.py
guisurfer/job/log.py
guisurfer/server/app.py
guisurfer/server/boot.py
guisurfer/server/hub.py
guisurfer/server/key.py
guisurfer/server/models.py
guisurfer/server/router/agents.py
guisurfer/server/router/desktops.py
guisurfer/server/router/job.py
guisurfer/server/router/keys.py
guisurfer/server/router/runtime.py
guisurfer/server/router/task.py
guisurfer/server/router/vnc.py
guisurfer/server/runtime.py
guisurfer/server/test.py
guisurfer-0.1.43.dist-info/METADATA
guisurfer-0.1.43.dist-info/WHEEL
guisurfer-0.1.43.dist-info/RECORD
