Metadata-Version: 2.1
Name: guisurfer
Version: 0.1.43
Summary: GUI surfing agents
License: Apache 2.0
Author: Patrick Barker
Author-email: patrickbarkerco@gmail.com
Requires-Python: >=3.10,<4.0
Classifier: License :: Other/Proprietary License
Classifier: Programming Language :: Python :: 3
Classifier: Programming Language :: Python :: 3.10
Classifier: Programming Language :: Python :: 3.11
Requires-Dist: agentdesk (>=0.2.43,<0.3.0)
Requires-Dist: asyncssh (>=2.14.2,<3.0.0)
Requires-Dist: authlib (>=1.3.0,<2.0.0)
Requires-Dist: cryptography (>=42.0.5,<43.0.0)
Requires-Dist: fastapi[all] (==0.109.0)
Requires-Dist: gunicorn (>=21.2.0,<22.0.0)
Requires-Dist: kubernetes (>=29.0.0,<30.0.0)
Requires-Dist: litellm (>=1.34.20,<2.0.0)
Requires-Dist: namesgenerator (>=0.3,<0.4)
Requires-Dist: rich (>=13.7.1,<14.0.0)
Requires-Dist: threadmem (>=0.2.11,<0.3.0)
Requires-Dist: websockets (>=12.0,<13.0)
